sliderule/__init__.py
sliderule/earthdata.py
sliderule/gedi.py
sliderule/h5.py
sliderule/icesat2.py
sliderule/io.py
sliderule/ipysliderule.py
sliderule/las.py
sliderule/raster.py
sliderule/session.py
sliderule/sliderule.py
sliderule/swot.py
sliderule/version.py
sliderule-5.0.1.data/scripts/3dep_gen_db.py
sliderule-5.0.1.data/scripts/atl13_generate_mappings.py
sliderule-5.0.1.data/scripts/atl13_utils.py
sliderule-5.0.1.data/scripts/atl24g_runner.py
sliderule-5.0.1.data/scripts/baseline.py
sliderule-5.0.1.data/scripts/benchmark.py
sliderule-5.0.1.data/scripts/create_geojson.py
sliderule-5.0.1.data/scripts/crs2projjson.py
sliderule-5.0.1.data/scripts/eight_day_cycle.py
sliderule-5.0.1.data/scripts/i2_optimize.py
sliderule-5.0.1.data/scripts/log_reformat.py
sliderule-5.0.1.data/scripts/lpdaac_download.py
sliderule-5.0.1.data/scripts/lpdaac_list.py
sliderule-5.0.1.data/scripts/opendata_worldcover.py
sliderule-5.0.1.data/scripts/stac_request.py
sliderule-5.0.1.data/scripts/trace_capture.py
sliderule-5.0.1.data/scripts/usage_report.py
sliderule-5.0.1.dist-info/licenses/LICENSE
tests/__init__.py
tests/conftest.py
tests/test_3dcrs.py
tests/test_3dep.py
tests/test_ancillary.py
tests/test_apis.py
tests/test_arcticdem.py
tests/test_arrow.py
tests/test_atl03_las.py
tests/test_atl03x.py
tests/test_atl03x_datum.py
tests/test_atl03x_sampling.py
tests/test_atl13x.py
tests/test_atl24x.py
tests/test_bluetopo.py
tests/test_defaults.py
tests/test_earthdata.py
tests/test_gebco.py
tests/test_gedi.py
tests/test_gedtm.py
tests/test_geo.py
tests/test_geojson.py
tests/test_globalcanopy.py
tests/test_h5.py
tests/test_h5p.py
tests/test_icesat2.py
tests/test_icesat2_viewer.py
tests/test_landsat.py
tests/test_luaerr.py
tests/test_meritdem.py
tests/test_parquet.py
tests/test_provisioning.py
tests/test_rema.py
tests/test_subsetting.py
tests/test_swot.py
tests/test_worldcover.py
sliderule-5.0.1.dist-info/METADATA
sliderule-5.0.1.dist-info/WHEEL
sliderule-5.0.1.dist-info/top_level.txt
sliderule-5.0.1.dist-info/RECORD
