Metadata-Version: 2.4
Name: sliderule
Version: 5.0.1
Summary: Python client for interacting with sliderule server
Home-page: https://github.com/SlideRuleEarth/sliderule/
Author: SlideRule Developers
License: BSD 3-Clause
Classifier: Development Status :: 3 - Alpha
Classifier: Intended Audience :: Science/Research
Classifier: Topic :: Scientific/Engineering :: Physics
Classifier: License :: OSI Approved :: BSD License
Classifier: Programming Language :: Python :: 3
Classifier: Programming Language :: Python :: 3.7
License-File: LICENSE
Requires-Dist: requests
Requires-Dist: numpy
Requires-Dist: geopandas
Requires-Dist: shapely
Requires-Dist: pyarrow
Dynamic: author
Dynamic: classifier
Dynamic: description-content-type
Dynamic: home-page
Dynamic: license
Dynamic: license-file
Dynamic: requires-dist
Dynamic: summary
